<?xml version="1.0" encoding="UTF-8" standalone="yes"?>


<!-- ================================================================================================================== -->
<!--   Chernarus types.xml organized by item type.  Sorted by DayZedAndConfsued762, DayZed and Confused DayZ Servers.   -->
<!--                                            https://discord.gg/UkHvV7j6kf                                           -->
<!-- ================================================================================================================== -->
<!-- -->
<!-- -->
<!-- -->
<!-- Categories: -->
<!-- -->
<!-- MEDICALS: -->
<!--   MEDICALS_SUPPLIES -->
<!-- -->
<!-- MISC -->
<!-- -->
<!-- TOOLS: -->
<!--  TOOLS_COMMUNICATION  TOOLS_ELECTRICAL  TOOLS_FARMING  TOOLS_FIRE  -->
<!--  TOOLS_HAND_MISC  TOOLS_LIGHTING  TOOLS_REPAIR  -->
<!-- -->
<!-- VEHICLES: -->
<!--  VEHICLES_PARTS  -->
<!-- -->


<types>


<!-- MEDICALS START -->

<!--  MEDICALS_MEDICINE -->

<!-- MEDICALS_SUPPLIES START -->

    <type name="CJ_FieldBandage_Small">
        <nominal>20</nominal>
        <lifetime>14400</lifetime>
        <restock>0</restock>
        <min>5</min>
        <quantmin>-1</quantmin>
        <quantmax>-1</quantmax>
        <cost>50</cost>
        <flags count_in_cargo="0" count_in_hoarder="0" count_in_map="1" count_in_player="0" crafted="0" deloot="0"/>
        <category name="tools"/>
        <tag name="shelves"/>
        <usage name="Military"/>
    </type>
    <type name="CJ_FieldBandage_Large">
        <nominal>10</nominal>
        <lifetime>14400</lifetime>
        <restock>0</restock>
        <min>5</min>
        <quantmin>-1</quantmin>
        <quantmax>-1</quantmax>
        <cost>50</cost>
        <flags count_in_cargo="0" count_in_hoarder="0" count_in_map="1" count_in_player="0" crafted="0" deloot="0"/>
        <category name="tools"/>
        <tag name="shelves"/>
        <usage name="Military"/>
    </type>
    <type name="CJ_FirstAidKit_Leather">
        <nominal>10</nominal>
        <lifetime>14400</lifetime>
        <restock>0</restock>
        <min>5</min>
        <quantmin>-1</quantmin>
        <quantmax>-1</quantmax>
        <cost>50</cost>
        <flags count_in_cargo="0" count_in_hoarder="0" count_in_map="1" count_in_player="0" crafted="0" deloot="0"/>
        <category name="containers"/>
        <tag name="shelves"/>
        <usage name="Medic"/>
    </type>
    <type name="CJ_FirstAidKit_Car">
        <nominal>15</nominal>
        <lifetime>14400</lifetime>
        <restock>0</restock>
        <min>10</min>
        <quantmin>-1</quantmin>
        <quantmax>-1</quantmax>
        <cost>50</cost>
        <flags count_in_cargo="0" count_in_hoarder="0" count_in_map="1" count_in_player="0" crafted="0" deloot="0"/>
        <category name="containers"/>
        <category name="tools"/>
        <tag name="shelves"/>
        <usage name="Industrial"/>
    </type>
    <type name="CJ_FirstAidKit_Grizzly">
        <nominal>5</nominal>
        <lifetime>14400</lifetime>
        <restock>0</restock>
        <min>5</min>
        <quantmin>-1</quantmin>
        <quantmax>-1</quantmax>
        <cost>50</cost>
        <flags count_in_cargo="0" count_in_hoarder="0" count_in_map="1" count_in_player="0" crafted="0" deloot="0"/>
        <category name="containers"/>
        <tag name="shelves"/>
        <usage name="Hunting"/>
    </type>
    <type name="CJ_SamSplint">
        <nominal>20</nominal>
        <lifetime>14400</lifetime>
        <restock>0</restock>
        <min>5</min>
        <quantmin>-1</quantmin>
        <quantmax>-1</quantmax>
        <cost>50</cost>
        <flags count_in_cargo="0" count_in_hoarder="0" count_in_map="1" count_in_player="0" crafted="0" deloot="0"/>
        <category name="tools"/>
        <tag name="shelves"/>
        <usage name="Medic"/>
    </type>

<!-- MEDICALS_SUPPLIES END -->

<!-- MEDICALS END -->

<!-- MISC START -->

    <type name="CJ_Cigarettes_1">
        <nominal>5</nominal>
        <lifetime>14400</lifetime>
        <restock>0</restock>
        <min>1</min>
        <quantmin>-1</quantmin>
        <quantmax>-1</quantmax>
        <cost>50</cost>
        <flags count_in_cargo="0" count_in_hoarder="0" count_in_map="1" count_in_player="0" crafted="0" deloot="0"/>
        <category name="containers"/>
        <usage name="Industrial"/>
        <usage name="Village"/>
        <usage name="Town"/>
    </type>
    <type name="CJ_Cigarettes_2">
        <nominal>5</nominal>
        <lifetime>14400</lifetime>
        <restock>0</restock>
        <min>1</min>
        <quantmin>-1</quantmin>
        <quantmax>-1</quantmax>
        <cost>50</cost>
        <flags count_in_cargo="0" count_in_hoarder="0" count_in_map="1" count_in_player="0" crafted="0" deloot="0"/>
        <category name="containers"/>
        <usage name="Industrial"/>
        <usage name="Village"/>
        <usage name="Town"/>
    </type>
    <type name="CJ_Cigarettes_3">
        <nominal>5</nominal>
        <lifetime>14400</lifetime>
        <restock>0</restock>
        <min>1</min>
        <quantmin>-1</quantmin>
        <quantmax>-1</quantmax>
        <cost>50</cost>
        <flags count_in_cargo="0" count_in_hoarder="0" count_in_map="1" count_in_player="0" crafted="0" deloot="0"/>
        <category name="containers"/>
        <usage name="Industrial"/>
        <usage name="Village"/>
        <usage name="Town"/>
    </type>
    <type name="CJ_Cigarettes_4">
        <nominal>5</nominal>
        <lifetime>14400</lifetime>
        <restock>0</restock>
        <min>1</min>
        <quantmin>-1</quantmin>
        <quantmax>-1</quantmax>
        <cost>50</cost>
        <flags count_in_cargo="0" count_in_hoarder="0" count_in_map="1" count_in_player="0" crafted="0" deloot="0"/>
        <category name="containers"/>
        <usage name="Industrial"/>
        <usage name="Village"/>
        <usage name="Town"/>
    </type>
    <type name="CJ_Cigarettes_5">
        <nominal>5</nominal>
        <lifetime>14400</lifetime>
        <restock>0</restock>
        <min>1</min>
        <quantmin>-1</quantmin>
        <quantmax>-1</quantmax>
        <cost>50</cost>
        <flags count_in_cargo="0" count_in_hoarder="0" count_in_map="1" count_in_player="0" crafted="0" deloot="0"/>
        <category name="containers"/>
        <usage name="Industrial"/>
        <usage name="Village"/>
        <usage name="Town"/>
    </type>



    <type name="CJ_VanishSpray">
        <nominal>10</nominal>
        <lifetime>14400</lifetime>
        <restock>0</restock>
        <min>5</min>
        <quantmin>10</quantmin>
        <quantmax>100</quantmax>
        <cost>50</cost>
        <flags count_in_cargo="0" count_in_hoarder="0" count_in_map="1" count_in_player="0" crafted="1" deloot="0"/>
        <category name="tools"/>
        <usage name="Town"/>
        <usage name="Village"/>
    </type>

    <type name="CJ_Toiletpaper">
        <nominal>50</nominal>
        <lifetime>14400</lifetime>
        <restock>0</restock>
        <min>5</min>
        <quantmin>10</quantmin>
        <quantmax>100</quantmax>
        <cost>50</cost>
        <flags count_in_cargo="0" count_in_hoarder="0" count_in_map="1" count_in_player="0" crafted="0" deloot="0"/>
        <category name="tools"/>
        <tag name="shelves"/>
        <usage name="Farm"/>
        <usage name="Town"/>
        <usage name="Village"/>
    </type>
    <type name="CJ_Isospray">
        <nominal>20</nominal>
        <lifetime>28800</lifetime>
        <restock>0</restock>
        <min>5</min>
        <quantmin>25</quantmin>
        <quantmax>100</quantmax>
        <cost>50</cost>
        <flags count_in_cargo="0" count_in_hoarder="0" count_in_map="1" count_in_player="0" crafted="0" deloot="0"/>
        <category name="tools"/>
        <tag name="shelves"/>
        <usage name="Industrial"/>
        <usage name="Town"/>
        <usage name="Village"/>
    </type>
    <type name="CJ_IsoTape">
        <nominal>20</nominal>
        <lifetime>28800</lifetime>
        <restock>0</restock>
        <min>5</min>
        <quantmin>25</quantmin>
        <quantmax>100</quantmax>
        <cost>50</cost>
        <flags count_in_cargo="0" count_in_hoarder="0" count_in_map="1" count_in_player="0" crafted="0" deloot="0"/>
        <category name="tools"/>
        <tag name="shelves"/>
        <usage name="Industrial"/>
        <usage name="Farm"/>
        <usage name="Town"/>
        <usage name="Village"/>
    </type>

<!-- MISC END -->

<!-- TOOLS START -->

<!-- TOOLS_COMMUNICATION START -->

    <type name="CJ_WalkieTalkie">
        <nominal>5</nominal>
        <lifetime>28800</lifetime>
        <restock>0</restock>
        <min>4</min>
        <quantmin>-1</quantmin>
        <quantmax>-1</quantmax>
        <cost>100</cost>
        <flags count_in_cargo="0" count_in_hoarder="0" count_in_map="1" count_in_player="0" crafted="0" deloot="0"/>
        <category name="tools"/>
        <tag name="shelves"/>
        <usage name="School"/>
        <usage name="Village"/>
        <usage name="Town"/>
    </type>
    <type name="CJ_Motorola_T80_Yellow">
        <nominal>4</nominal>
        <lifetime>28800</lifetime>
        <restock>0</restock>
        <min>2</min>
        <quantmin>-1</quantmin>
        <quantmax>-1</quantmax>
        <cost>100</cost>
        <flags count_in_cargo="0" count_in_hoarder="0" count_in_map="1" count_in_player="0" crafted="0" deloot="0"/>
        <category name="tools"/>
        <tag name="shelves"/>
        <usage name="Village"/>
        <usage name="Town"/>
    </type>
    <type name="CJ_Motorola_T80_Red">
        <nominal>4</nominal>
        <lifetime>28800</lifetime>
        <restock>0</restock>
        <min>1</min>
        <quantmin>-1</quantmin>
        <quantmax>-1</quantmax>
        <cost>100</cost>
        <flags count_in_cargo="0" count_in_hoarder="0" count_in_map="1" count_in_player="0" crafted="0" deloot="0"/>
        <category name="tools"/>
        <tag name="shelves"/>
        <usage name="Firefighter"/>
    </type>
    <type name="CJ_Motorola_T80_Blue">
        <nominal>7</nominal>
        <lifetime>28800</lifetime>
        <restock>0</restock>
        <min>5</min>
        <quantmin>-1</quantmin>
        <quantmax>-1</quantmax>
        <cost>100</cost>
        <flags count_in_cargo="0" count_in_hoarder="0" count_in_map="1" count_in_player="0" crafted="0" deloot="0"/>
        <category name="tools"/>
        <tag name="shelves"/>
        <usage name="Police"/>
    </type>
    <type name="CJ_Motorola_T80_Green">
        <nominal>4</nominal>
        <lifetime>28800</lifetime>
        <restock>0</restock>
        <min>2</min>
        <quantmin>-1</quantmin>
        <quantmax>-1</quantmax>
        <cost>100</cost>
        <flags count_in_cargo="0" count_in_hoarder="0" count_in_map="1" count_in_player="0" crafted="0" deloot="0"/>
        <category name="tools"/>
        <tag name="shelves"/>
        <usage name="Military"/>
    </type>
    <type name="CJ_Motorola_T80_Lime">
        <nominal>4</nominal>
        <lifetime>28800</lifetime>
        <restock>0</restock>
        <min>2</min>
        <quantmin>-1</quantmin>
        <quantmax>-1</quantmax>
        <cost>100</cost>
        <flags count_in_cargo="0" count_in_hoarder="0" count_in_map="1" count_in_player="0" crafted="0" deloot="0"/>
        <category name="tools"/>
        <tag name="shelves"/>
        <usage name="Village"/>
        <usage name="Town"/>
    </type>
    <type name="CJ_Motorola_T80_Grey">
        <nominal>6</nominal>
        <lifetime>28800</lifetime>
        <restock>0</restock>
        <min>5</min>
        <quantmin>-1</quantmin>
        <quantmax>-1</quantmax>
        <cost>100</cost>
        <flags count_in_cargo="0" count_in_hoarder="0" count_in_map="1" count_in_player="0" crafted="0" deloot="0"/>
        <category name="tools"/>
        <tag name="shelves"/>
        <usage name="Village"/>
        <usage name="School"/>
        <usage name="Town"/>
    </type>
    <type name="CJ_Falcon3_Radio">
        <nominal>3</nominal>
        <lifetime>28800</lifetime>
        <restock>0</restock>
        <min>1</min>
        <quantmin>-1</quantmin>
        <quantmax>-1</quantmax>
        <cost>50</cost>
        <flags count_in_cargo="0" count_in_hoarder="0" count_in_map="1" count_in_player="0" crafted="0" deloot="0"/>
        <category name="tools"/>
        <tag name="shelves"/>
        <usage name="Military"/>
    </type>
    <type name="CJ_TacSatRadio_Black">
        <nominal>3</nominal>
        <lifetime>28800</lifetime>
        <restock>0</restock>
        <min>1</min>
        <quantmin>-1</quantmin>
        <quantmax>-1</quantmax>
        <cost>50</cost>
        <flags count_in_cargo="0" count_in_hoarder="0" count_in_map="1" count_in_player="0" crafted="0" deloot="0"/>
        <category name="tools"/>
        <tag name="shelves"/>
        <usage name="Military"/>
    </type>
    <type name="CJ_TacSatRadio_Green">
        <nominal>3</nominal>
        <lifetime>28800</lifetime>
        <restock>0</restock>
        <min>1</min>
        <quantmin>-1</quantmin>
        <quantmax>-1</quantmax>
        <cost>50</cost>
        <flags count_in_cargo="0" count_in_hoarder="0" count_in_map="1" count_in_player="0" crafted="0" deloot="0"/>
        <category name="tools"/>
        <tag name="shelves"/>
        <usage name="Military"/>
    </type>
    <type name="CJ_TacSatRadio_Tan">
        <nominal>3</nominal>
        <lifetime>28800</lifetime>
        <restock>0</restock>
        <min>1</min>
        <quantmin>-1</quantmin>
        <quantmax>-1</quantmax>
        <cost>50</cost>
        <flags count_in_cargo="0" count_in_hoarder="0" count_in_map="1" count_in_player="0" crafted="0" deloot="0"/>
        <category name="tools"/>
        <tag name="shelves"/>
        <usage name="Military"/>
    </type>

<!-- TOOLS_COMMUNICATION END -->

<!-- TOOLS_ELECTRICAL START -->

    <type name="CJ_Battery9V_1">
        <nominal>10</nominal>
        <lifetime>14400</lifetime>
        <restock>0</restock>
        <min>5</min>
        <quantmin>50</quantmin>
        <quantmax>100</quantmax>
        <cost>50</cost>
        <flags count_in_cargo="0" count_in_hoarder="0" count_in_map="1" count_in_player="0" crafted="0" deloot="0"/>
        <category name="tools"/>
        <tag name="shelves"/>
        <usage name="Industrial"/>
        <usage name="Village"/>
    </type>
    <type name="CJ_Battery9V_2">
        <nominal>10</nominal>
        <lifetime>14400</lifetime>
        <restock>0</restock>
        <min>5</min>
        <quantmin>50</quantmin>
        <quantmax>100</quantmax>
        <cost>50</cost>
        <flags count_in_cargo="0" count_in_hoarder="0" count_in_map="1" count_in_player="0" crafted="0" deloot="0"/>
        <category name="tools"/>
        <tag name="shelves"/>
        <usage name="Industrial"/>
        <usage name="Village"/>
    </type>
    <type name="CJ_Battery9V_3">
        <nominal>10</nominal>
        <lifetime>14400</lifetime>
        <restock>0</restock>
        <min>5</min>
        <quantmin>50</quantmin>
        <quantmax>100</quantmax>
        <cost>50</cost>
        <flags count_in_cargo="0" count_in_hoarder="0" count_in_map="1" count_in_player="0" crafted="0" deloot="0"/>
        <category name="tools"/>
        <tag name="shelves"/>
        <usage name="Industrial"/>
        <usage name="Village"/>
    </type>
    <type name="CJ_Battery9V_4">
        <nominal>10</nominal>
        <lifetime>14400</lifetime>
        <restock>0</restock>
        <min>5</min>
        <quantmin>50</quantmin>
        <quantmax>100</quantmax>
        <cost>50</cost>
        <flags count_in_cargo="0" count_in_hoarder="0" count_in_map="1" count_in_player="0" crafted="0" deloot="0"/>
        <category name="tools"/>
        <tag name="shelves"/>
        <usage name="Industrial"/>
        <usage name="Village"/>
    </type>
    <type name="CJ_MilBattery_Black">
        <nominal>5</nominal>
        <lifetime>14400</lifetime>
        <restock>0</restock>
        <min>2</min>
        <quantmin>50</quantmin>
        <quantmax>100</quantmax>
        <cost>50</cost>
        <flags count_in_cargo="0" count_in_hoarder="0" count_in_map="1" count_in_player="0" crafted="0" deloot="0"/>
        <category name="tools"/>
        <tag name="shelves"/>
        <usage name="Military"/>
    </type>
    <type name="CJ_MilBattery_Green">
        <nominal>5</nominal>
        <lifetime>14400</lifetime>
        <restock>0</restock>
        <min>2</min>
        <quantmin>50</quantmin>
        <quantmax>100</quantmax>
        <cost>50</cost>
        <flags count_in_cargo="0" count_in_hoarder="0" count_in_map="1" count_in_player="0" crafted="0" deloot="0"/>
        <category name="tools"/>
        <tag name="shelves"/>
        <usage name="Military"/>
    </type>
    <type name="CJ_MilBattery_Tan">
        <nominal>5</nominal>
        <lifetime>14400</lifetime>
        <restock>0</restock>
        <min>2</min>
        <quantmin>50</quantmin>
        <quantmax>100</quantmax>
        <cost>50</cost>
        <flags count_in_cargo="0" count_in_hoarder="0" count_in_map="1" count_in_player="0" crafted="0" deloot="0"/>
        <category name="tools"/>
        <tag name="shelves"/>
        <usage name="Military"/>
    </type>

<!-- TOOLS_ELECTRICAL END -->

<!-- TOOLS_FARMING START -->

    <type name="CJ_AntiPestsSpray_1">
        <nominal>0</nominal>
        <lifetime>14400</lifetime>
        <restock>0</restock>
        <min>0</min>
        <quantmin>10</quantmin>
        <quantmax>100</quantmax>
        <cost>50</cost>
        <flags count_in_cargo="0" count_in_hoarder="0" count_in_map="1" count_in_player="0" crafted="1" deloot="0"/>
        <category name="tools"/>
        <usage name="Farm"/>
        <usage name="Town"/>
        <usage name="Village"/>
    </type>
    <type name="CJ_AntiPestsSpray_2">
        <nominal>0</nominal>
        <lifetime>14400</lifetime>
        <restock>0</restock>
        <min>0</min>
        <quantmin>10</quantmin>
        <quantmax>100</quantmax>
        <cost>50</cost>
        <flags count_in_cargo="0" count_in_hoarder="0" count_in_map="1" count_in_player="0" crafted="1" deloot="0"/>
        <category name="tools"/>
        <usage name="Farm"/>
        <usage name="Town"/>
        <usage name="Village"/>
    </type>
    <type name="CJ_AntiPestsSpray_3">
        <nominal>0</nominal>
        <lifetime>14400</lifetime>
        <restock>0</restock>
        <min>0</min>
        <quantmin>10</quantmin>
        <quantmax>100</quantmax>
        <cost>50</cost>
        <flags count_in_cargo="0" count_in_hoarder="0" count_in_map="1" count_in_player="0" crafted="1" deloot="0"/>
        <category name="tools"/>
        <usage name="Farm"/>
        <usage name="Town"/>
        <usage name="Village"/>
    </type>
    <type name="CJ_GardenLime_1">
        <nominal>10</nominal>
        <lifetime>14400</lifetime>
        <restock>0</restock>
        <min>5</min>
        <quantmin>25</quantmin>
        <quantmax>100</quantmax>
        <cost>50</cost>
        <flags count_in_cargo="0" count_in_hoarder="0" count_in_map="1" count_in_player="0" crafted="0" deloot="0"/>
        <category name="tools"/>
        <usage name="Farm"/>
    </type>
    <type name="CJ_GardenLime_2">
        <nominal>10</nominal>
        <lifetime>14400</lifetime>
        <restock>0</restock>
        <min>5</min>
        <quantmin>25</quantmin>
        <quantmax>100</quantmax>
        <cost>50</cost>
        <flags count_in_cargo="0" count_in_hoarder="0" count_in_map="1" count_in_player="0" crafted="0" deloot="0"/>
        <category name="tools"/>
        <usage name="Farm"/>
    </type>
    <type name="CJ_GardenLime_3">
        <nominal>10</nominal>
        <lifetime>14400</lifetime>
        <restock>0</restock>
        <min>5</min>
        <quantmin>25</quantmin>
        <quantmax>100</quantmax>
        <cost>50</cost>
        <flags count_in_cargo="0" count_in_hoarder="0" count_in_map="1" count_in_player="0" crafted="0" deloot="0"/>
        <category name="tools"/>
        <usage name="Farm"/>
    </type>
    <type name="CJ_GardenLime_4">
        <nominal>10</nominal>
        <lifetime>14400</lifetime>
        <restock>0</restock>
        <min>5</min>
        <quantmin>25</quantmin>
        <quantmax>100</quantmax>
        <cost>50</cost>
        <flags count_in_cargo="0" count_in_hoarder="0" count_in_map="1" count_in_player="0" crafted="0" deloot="0"/>
        <category name="tools"/>
        <usage name="Farm"/>
    </type>

<!-- TOOLS_FARMING END -->

<!-- TOOLS_FIRE START -->

    <type name="CJ_ButaneCanister">
        <nominal>10</nominal>
        <lifetime>14400</lifetime>
        <restock>0</restock>
        <min>5</min>
        <quantmin>65</quantmin>
        <quantmax>100</quantmax>
        <cost>50</cost>
        <flags count_in_cargo="0" count_in_hoarder="0" count_in_map="1" count_in_player="0" crafted="0" deloot="0"/>
        <category name="tools"/>
        <usage name="Village"/>
        <usage name="Hunting"/>
    </type>
    <type name="CJ_GasBottle">
        <nominal>5</nominal>
        <lifetime>28800</lifetime>
        <restock>0</restock>
        <min>5</min>
        <quantmin>50</quantmin>
        <quantmax>100</quantmax>
        <cost>15</cost>
        <flags count_in_cargo="0" count_in_hoarder="0" count_in_map="1" count_in_player="0" crafted="0" deloot="0"/>
        <category name="tools"/>
        <tag name="shelves"/>
        <usage name="Industrial"/>
        <usage name="Farm"/>
        <usage name="Village"/>
    </type>

<!-- TOOLS_FIRE END -->

<!-- TOOLS_HAND_MISC START -->

    <type name="CJ_Pliers_Yellow">
        <nominal>20</nominal>
        <lifetime>14400</lifetime>
        <restock>0</restock>
        <min>5</min>
        <quantmin>-1</quantmin>
        <quantmax>-1</quantmax>
        <cost>50</cost>
        <flags count_in_cargo="0" count_in_hoarder="0" count_in_map="1" count_in_player="0" crafted="0" deloot="0"/>
        <category name="tools"/>
        <usage name="Industrial"/>
        <usage name="Farm"/>
        <usage name="Village"/>
    </type>
    <type name="CJ_Pliers_Red">
        <nominal>20</nominal>
        <lifetime>14400</lifetime>
        <restock>0</restock>
        <min>5</min>
        <quantmin>-1</quantmin>
        <quantmax>-1</quantmax>
        <cost>50</cost>
        <flags count_in_cargo="0" count_in_hoarder="0" count_in_map="1" count_in_player="0" crafted="0" deloot="0"/>
        <category name="tools"/>
        <usage name="Industrial"/>
        <usage name="Farm"/>
        <usage name="Village"/>
    </type>
    <type name="CJ_Screwdriver_Red">
        <nominal>25</nominal>
        <lifetime>14400</lifetime>
        <restock>0</restock>
        <min>5</min>
        <quantmin>50</quantmin>
        <quantmax>100</quantmax>
        <cost>50</cost>
        <flags count_in_cargo="0" count_in_hoarder="0" count_in_map="1" count_in_player="0" crafted="0" deloot="0"/>
        <category name="tools"/>
        <usage name="Industrial"/>
        <usage name="Farm"/>
        <usage name="Village"/>
    </type>

<!-- TOOLS_HAND_MISC END -->

<!-- TOOLS_LIGHTING START -->

    <type name="CJ_Flashlight_Yellow">
        <nominal>30</nominal>
        <lifetime>14400</lifetime>
        <restock>0</restock>
        <min>15</min>
        <quantmin>-1</quantmin>
        <quantmax>-1</quantmax>
        <cost>100</cost>
        <flags count_in_cargo="0" count_in_hoarder="0" count_in_map="1" count_in_player="0" crafted="0" deloot="0"/>
        <category name="tools"/>
        <tag name="shelves"/>
    </type>

<!-- TOOLS_LIGHTING END -->

<!-- TOOLS_REPAIR START -->

    <type name="CJ_ToolsRepairKit">
        <nominal>20</nominal>
        <lifetime>28800</lifetime>
        <restock>0</restock>
        <min>5</min>
        <quantmin>10</quantmin>
        <quantmax>100</quantmax>
        <cost>50</cost>
        <flags count_in_cargo="0" count_in_hoarder="0" count_in_map="1" count_in_player="0" crafted="0" deloot="0"/>
        <category name="tools"/>
        <tag name="shelves"/>
        <usage name="Farm"/>
        <usage name="Town"/>
        <usage name="Village"/>
    </type>
    <type name="CJ_WD40_Small">
        <nominal>30</nominal>
        <lifetime>28800</lifetime>
        <restock>0</restock>
        <min>15</min>
        <quantmin>25</quantmin>
        <quantmax>100</quantmax>
        <cost>50</cost>
        <flags count_in_cargo="0" count_in_hoarder="0" count_in_map="1" count_in_player="0" crafted="0" deloot="0"/>
        <category name="tools"/>
        <tag name="shelves"/>
        <usage name="Industrial"/>
        <usage name="Farm"/>
        <usage name="Town"/>
        <usage name="Village"/>
        <usage name="Hunting"/>
    </type>
    <type name="CJ_WD40_Large">
        <nominal>15</nominal>
        <lifetime>28800</lifetime>
        <restock>0</restock>
        <min>5</min>
        <quantmin>25</quantmin>
        <quantmax>100</quantmax>
        <cost>50</cost>
        <flags count_in_cargo="0" count_in_hoarder="0" count_in_map="1" count_in_player="0" crafted="0" deloot="0"/>
        <category name="tools"/>
        <tag name="shelves"/>
        <usage name="Industrial"/>
        <usage name="Farm"/>
        <usage name="Town"/>
        <usage name="Village"/>
        <usage name="Hunting"/>
    </type>
    <type name="CJ_Tireglue">
        <nominal>20</nominal>
        <lifetime>28800</lifetime>
        <restock>0</restock>
        <min>5</min>
        <quantmin>25</quantmin>
        <quantmax>100</quantmax>
        <cost>50</cost>
        <flags count_in_cargo="0" count_in_hoarder="0" count_in_map="1" count_in_player="0" crafted="0" deloot="0"/>
        <category name="tools"/>
        <tag name="shelves"/>
        <usage name="Industrial"/>
        <usage name="Farm"/>
    </type>
    <type name="CJ_Sewingspool_Red">
        <nominal>20</nominal>
        <lifetime>28800</lifetime>
        <restock>0</restock>
        <min>5</min>
        <quantmin>25</quantmin>
        <quantmax>100</quantmax>
        <cost>50</cost>
        <flags count_in_cargo="0" count_in_hoarder="0" count_in_map="1" count_in_player="0" crafted="0" deloot="0"/>
        <category name="tools"/>
        <tag name="shelves"/>
        <usage name="Farm"/>
        <usage name="Town"/>
        <usage name="Village"/>
    </type>
    <type name="CJ_Sewingspool_Blue">
        <nominal>20</nominal>
        <lifetime>28800</lifetime>
        <restock>0</restock>
        <min>5</min>
        <quantmin>25</quantmin>
        <quantmax>100</quantmax>
        <cost>50</cost>
        <flags count_in_cargo="0" count_in_hoarder="0" count_in_map="1" count_in_player="0" crafted="0" deloot="0"/>
        <category name="tools"/>
        <tag name="shelves"/>
        <usage name="Farm"/>
        <usage name="Town"/>
        <usage name="Village"/>
    </type>
    <type name="CJ_Sewingspool_Green">
        <nominal>20</nominal>
        <lifetime>28800</lifetime>
        <restock>0</restock>
        <min>5</min>
        <quantmin>25</quantmin>
        <quantmax>100</quantmax>
        <cost>50</cost>
        <flags count_in_cargo="0" count_in_hoarder="0" count_in_map="1" count_in_player="0" crafted="0" deloot="0"/>
        <category name="tools"/>
        <tag name="shelves"/>
        <usage name="Farm"/>
        <usage name="Town"/>
        <usage name="Village"/>
    </type>
    <type name="CJ_Weaponoil">
        <nominal>20</nominal>
        <lifetime>28800</lifetime>
        <restock>0</restock>
        <min>5</min>
        <quantmin>25</quantmin>
        <quantmax>100</quantmax>
        <cost>50</cost>
        <flags count_in_cargo="0" count_in_hoarder="0" count_in_map="1" count_in_player="0" crafted="0" deloot="0"/>
        <category name="tools"/>
        <tag name="shelves"/>
        <usage name="Farm"/>
        <usage name="Town"/>
        <usage name="Village"/>
        <usage name="Hunting"/>
    </type>

<!-- TOOLS_REPAIR END -->

<!-- TOOLS END -->



<!-- VEHICLES START -->

<!-- VEHICLES_PARTS START -->

    <type name="CJ_Sparkplug_Box_1">
        <nominal>15</nominal>
        <lifetime>14400</lifetime>
        <restock>0</restock>
        <min>5</min>
        <quantmin>-1</quantmin>
        <quantmax>-1</quantmax>
        <cost>50</cost>
        <flags count_in_cargo="0" count_in_hoarder="0" count_in_map="1" count_in_player="0" crafted="0" deloot="0"/>
        <category name="tools"/>
        <tag name="shelves"/>
        <usage name="Industrial"/>
    </type>
    <type name="CJ_Sparkplug_Box_2">
        <nominal>15</nominal>
        <lifetime>14400</lifetime>
        <restock>0</restock>
        <min>5</min>
        <quantmin>-1</quantmin>
        <quantmax>-1</quantmax>
        <cost>50</cost>
        <flags count_in_cargo="0" count_in_hoarder="0" count_in_map="1" count_in_player="0" crafted="0" deloot="0"/>
        <category name="tools"/>
        <tag name="shelves"/>
        <usage name="Industrial"/>
    </type>

<!-- VEHICLES_PARTS END -->

<!-- VEHICLES END -->

</types>