{
    "m_Version": 12,
    "DisplayName": "Black Market Optics",
    "Icon": "Deliver",
    "Color": "FBFCFEFF",
    "IsExchange": 0,
    "InitStockPercent": 75.0,
    "Items": [
        {
            "ClassName": "Candy_98S_Optic",
            "MaxPriceThreshold": 100000,
            "MinPriceThreshold": 100000,
            "SellPricePercent": -1.0,
            "MaxStockThreshold": 1,
            "MinStockThreshold": 1,
            "QuantityPercent": -1,
            "SpawnAttachments": [],
            "Variants": []
        },
        {
            "ClassName": "Candy_Barsuk_Optic",
            "MaxPriceThreshold": 100000,
            "MinPriceThreshold": 100000,
            "SellPricePercent": -1.0,
            "MaxStockThreshold": 1,
            "MinStockThreshold": 1,
            "QuantityPercent": -1,
            "SpawnAttachments": [],
            "Variants": []
        },
        {
            "ClassName": "Candy_BR_Optic",
            "MaxPriceThreshold": 100000,
            "MinPriceThreshold": 100000,
            "SellPricePercent": -1.0,
            "MaxStockThreshold": 1,
            "MinStockThreshold": 1,
            "QuantityPercent": -1,
            "SpawnAttachments": [],
            "Variants": []
        },
        {
            "ClassName": "Candy_DKS501_Optic",
            "MaxPriceThreshold": 100000,
            "MinPriceThreshold": 100000,
            "SellPricePercent": -1.0,
            "MaxStockThreshold": 1,
            "MinStockThreshold": 1,
            "QuantityPercent": -1,
            "SpawnAttachments": [],
            "Variants": []
        },
        {
            "ClassName": "Candy_FLINT_Optic",
            "MaxPriceThreshold": 100000,
            "MinPriceThreshold": 100000,
            "SellPricePercent": -1.0,
            "MaxStockThreshold": 1,
            "MinStockThreshold": 1,
            "QuantityPercent": -1,
            "SpawnAttachments": [],
            "Variants": []
        },
        {
            "ClassName": "Candy_GS15_Optic",
            "MaxPriceThreshold": 100000,
            "MinPriceThreshold": 100000,
            "SellPricePercent": -1.0,
            "MaxStockThreshold": 1,
            "MinStockThreshold": 1,
            "QuantityPercent": -1,
            "SpawnAttachments": [],
            "Variants": []
        },
        {
            "ClassName": "Candy_GX_Optic",
            "MaxPriceThreshold": 100000,
            "MinPriceThreshold": 100000,
            "SellPricePercent": -1.0,
            "MaxStockThreshold": 1,
            "MinStockThreshold": 1,
            "QuantityPercent": -1,
            "SpawnAttachments": [],
            "Variants": []
        },
        {
            "ClassName": "Candy_HAMR_Optic",
            "MaxPriceThreshold": 100000,
            "MinPriceThreshold": 100000,
            "SellPricePercent": -1.0,
            "MaxStockThreshold": 1,
            "MinStockThreshold": 1,
            "QuantityPercent": -1,
            "SpawnAttachments": [],
            "Variants": []
        },
        {
            "ClassName": "Candy_Leupold_Optic",
            "MaxPriceThreshold": 100000,
            "MinPriceThreshold": 100000,
            "SellPricePercent": -1.0,
            "MaxStockThreshold": 1,
            "MinStockThreshold": 1,
            "QuantityPercent": -1,
            "SpawnAttachments": [],
            "Variants": []
        },
        {
            "ClassName": "Candy_M900_Optic",
            "MaxPriceThreshold": 100000,
            "MinPriceThreshold": 100000,
            "SellPricePercent": -1.0,
            "MaxStockThreshold": 1,
            "MinStockThreshold": 1,
            "QuantityPercent": -1,
            "SpawnAttachments": [],
            "Variants": []
        },
        {
            "ClassName": "Candy_MD_Optic",
            "MaxPriceThreshold": 100000,
            "MinPriceThreshold": 100000,
            "SellPricePercent": -1.0,
            "MaxStockThreshold": 1,
            "MinStockThreshold": 1,
            "QuantityPercent": -1,
            "SpawnAttachments": [],
            "Variants": []
        },
        {
            "ClassName": "Candy_Razor_Optic",
            "MaxPriceThreshold": 100000,
            "MinPriceThreshold": 100000,
            "SellPricePercent": -1.0,
            "MaxStockThreshold": 1,
            "MinStockThreshold": 1,
            "QuantityPercent": -1,
            "SpawnAttachments": [],
            "Variants": []
        },
        {
            "ClassName": "Candy_SC_Optic",
            "MaxPriceThreshold": 100000,
            "MinPriceThreshold": 100000,
            "SellPricePercent": -1.0,
            "MaxStockThreshold": 1,
            "MinStockThreshold": 1,
            "QuantityPercent": -1,
            "SpawnAttachments": [],
            "Variants": []
        },
        {
            "ClassName": "Candy_SN_Optic",
            "MaxPriceThreshold": 100000,
            "MinPriceThreshold": 100000,
            "SellPricePercent": -1.0,
            "MaxStockThreshold": 1,
            "MinStockThreshold": 1,
            "QuantityPercent": -1,
            "SpawnAttachments": [],
            "Variants": []
        },
        {
            "ClassName": "Candy_SPIT_Optic",
            "MaxPriceThreshold": 100000,
            "MinPriceThreshold": 100000,
            "SellPricePercent": -1.0,
            "MaxStockThreshold": 1,
            "MinStockThreshold": 1,
            "QuantityPercent": -1,
            "SpawnAttachments": [],
            "Variants": []
        },
        {
            "ClassName": "Candy_SRR_Optic",
            "MaxPriceThreshold": 100000,
            "MinPriceThreshold": 100000,
            "SellPricePercent": -1.0,
            "MaxStockThreshold": 1,
            "MinStockThreshold": 1,
            "QuantityPercent": -1,
            "SpawnAttachments": [],
            "Variants": []
        },
        {
            "ClassName": "Candy_SSZ_Optic",
            "MaxPriceThreshold": 100000,
            "MinPriceThreshold": 100000,
            "SellPricePercent": -1.0,
            "MaxStockThreshold": 1,
            "MinStockThreshold": 1,
            "QuantityPercent": -1,
            "SpawnAttachments": [],
            "Variants": []
        },
        {
            "ClassName": "Candy_SW_Optic",
            "MaxPriceThreshold": 100000,
            "MinPriceThreshold": 100000,
            "SellPricePercent": -1.0,
            "MaxStockThreshold": 1,
            "MinStockThreshold": 1,
            "QuantityPercent": -1,
            "SpawnAttachments": [],
            "Variants": []
        },
        {
            "ClassName": "Candy_TA11_Optic",
            "MaxPriceThreshold": 100000,
            "MinPriceThreshold": 100000,
            "SellPricePercent": -1.0,
            "MaxStockThreshold": 1,
            "MinStockThreshold": 1,
            "QuantityPercent": -1,
            "SpawnAttachments": [],
            "Variants": []
        },
        {
            "ClassName": "Candy_UH1_Optic",
            "MaxPriceThreshold": 100000,
            "MinPriceThreshold": 100000,
            "SellPricePercent": -1.0,
            "MaxStockThreshold": 1,
            "MinStockThreshold": 1,
            "QuantityPercent": -1,
            "SpawnAttachments": [],
            "Variants": []
        }
    ]
}