{
    "m_Version": 12,
    "DisplayName": "UFSE SMGs",
    "Icon": "Deliver",
    "Color": "FBFCFEFF",
    "IsExchange": 0,
    "InitStockPercent": 100.0,
    "Items": [
        {
            "ClassName": "Candy_MP5",
            "MaxPriceThreshold": 300000,
            "MinPriceThreshold": 300000,
            "SellPricePercent": -1,
            "MaxStockThreshold": 1,
            "MinStockThreshold": 1,
            "QuantityPercent": -1,
            "SpawnAttachments": [],
            "Variants": []
        },
        {
            "ClassName": "Candy_Kriss",
            "MaxPriceThreshold": 300000,
            "MinPriceThreshold": 300000,
            "SellPricePercent": -1,
            "MaxStockThreshold": 1,
            "MinStockThreshold": 1,
            "QuantityPercent": -1,
            "SpawnAttachments": [],
            "Variants": []
        }
    ]
}