{
    "m_Version": 12,
    "DisplayName": "License Plates",
    "Icon": "Deliver",
    "Color": "FBFCFEFF",
    "IsExchange": 0,
    "InitStockPercent": 50.0,
    "Items": [
        {
            "ClassName": "vg7_scorpion_plate_usa",
            "MaxPriceThreshold": 1500,
            "MinPriceThreshold": 750,
            "SellPricePercent": -1.0,
            "MaxStockThreshold": 100,
            "MinStockThreshold": 1,
            "QuantityPercent": -1,
            "SpawnAttachments": [],
            "Variants": [
                "vg7_scorpion_plate_canada",
                "vg7_scorpion_plate_british",
                "vg7_scorpion_plate_china",
                "vg7_scorpion_plate_russia",
                "vg7_scorpion_plate_skull",
                "vg7_scorpion_plate_mermaid",
                "vg7_scorpion_plate_butterfly",
                "vg7_scorpion_plate_australia",
                "vg7_scorpion_plate_czechoslovakia",
                "vg7_scorpion_plate_blackouts",
                "vg7_scorpion_plate_mexico",
                "vg7_scorpion_plate_india"
            ]
        }
    ]
}