{
    "m_Version": 12,
    "DisplayName": "Sniper Rifles",
    "Icon": "Deliver",
    "Color": "FBFCFEFF",
    "IsExchange": 0,
    "InitStockPercent": 25.0,
    "Items": [
        {
            "ClassName": "b95",
            "MaxPriceThreshold": 30000,
            "MinPriceThreshold": 20000,
            "SellPricePercent": -1.0,
            "MaxStockThreshold": 2500,
            "MinStockThreshold": 1,
            "QuantityPercent": -1,
            "SpawnAttachments": [],
            "Variants": [
                "B95_Black",
                "B95_Green"
            ]
        },
        {
            "ClassName": "svd",
            "MaxPriceThreshold": 100000,
            "MinPriceThreshold": 90000,
            "SellPricePercent": -1.0,
            "MaxStockThreshold": 2500,
            "MinStockThreshold": 1,
            "QuantityPercent": -1,
            "SpawnAttachments": [],
            "Variants": []
        },
        {
            "ClassName": "sv98",
            "MaxPriceThreshold": 100000,
            "MinPriceThreshold": 90000,
            "SellPricePercent": -1.0,
            "MaxStockThreshold": 2500,
            "MinStockThreshold": 1,
            "QuantityPercent": -1,
            "SpawnAttachments": [],
            "Variants": []
        },
        {
            "ClassName": "scout",
            "MaxPriceThreshold": 50000,
            "MinPriceThreshold": 40000,
            "SellPricePercent": -1.0,
            "MaxStockThreshold": 2500,
            "MinStockThreshold": 1,
            "QuantityPercent": -1,
            "SpawnAttachments": [],
            "Variants": [
                "Scout_Chernarus",
                "Scout_Livonia"
            ]
        },
        {
            "ClassName": "expansion_awm",
            "MaxPriceThreshold": 120000,
            "MinPriceThreshold": 50000,
            "SellPricePercent": -1.0,
            "MaxStockThreshold": 2500,
            "MinStockThreshold": 1,
            "QuantityPercent": -1,
            "SpawnAttachments": [],
            "Variants": []
        }
    ]
}