{
  "name": "black",
  "spawnWeight": 1,
  "characterTypes": [
"SurvivorM_Mirek",
      "SurvivorM_Boris",
      "SurvivorM_Cyril",
      "SurvivorM_Denis",
      "SurvivorM_Elias",
      "SurvivorM_Francis",
      "SurvivorM_Guo",
      "SurvivorM_Hassan",
      "SurvivorM_Indar",
      "SurvivorM_Jose",
      "SurvivorM_Kaito",
      "SurvivorM_Lewis",
      "SurvivorM_Manua",
      "SurvivorM_Niki",
      "SurvivorM_Oliver",
      "SurvivorM_Peter",
      "SurvivorM_Quinn",
      "SurvivorM_Rolf",
      "SurvivorM_Seth",
      "SurvivorM_Taiki",
      "SurvivorF_Eva",
      "SurvivorF_Frida",
      "SurvivorF_Gabi",
      "SurvivorF_Helga",
      "SurvivorF_Irena",
      "SurvivorF_Judy",
      "SurvivorF_Keiko",
      "SurvivorF_Linda",
      "SurvivorF_Maria",
      "SurvivorF_Naomi",
      "SurvivorF_Baty"],
  "attachmentSlotItemSets": [
    {
      "slotName": "Headgear",
      "discreteItemSets": [
        {
          "itemType": "BaseballCap_Black",
          "spawnWeight": 1,
          "attributes": {
            "healthMin": 1,
            "healthMax": 1,
            "quantityMin": 1,
            "quantityMax": 1
          },
          "quickBarSlot": -1,
          "simpleChildrenUseDefaultAttributes": false,
          "simpleChildrenTypes": [],
          "complexChildrenTypes": []
        }
      ]
    },
    {
      "slotName": "Armband",
      "discreteItemSets": [
        {
          "itemType": "Armband_Snake",
          "spawnWeight": 1,
          "attributes": {
            "healthMin": 1,
            "healthMax": 1,
            "quantityMin": 1,
            "quantityMax": 1
          },
          "quickBarSlot": -1,
          "simpleChildrenUseDefaultAttributes": false,
          "simpleChildrenTypes": [],
          "complexChildrenTypes": []
        }
      ]
    },
    {
      "slotName": "Body",
      "discreteItemSets": [
        {
          "itemType": "FirefighterJacket_Black",
          "spawnWeight": 1,
          "attributes": {
            "healthMin": 1,
            "healthMax": 1,
            "quantityMin": 1,
            "quantityMax": 1
          },
          "quickBarSlot": -1,
          "simpleChildrenUseDefaultAttributes": false,
          "simpleChildrenTypes": [
            "SodaCan_Spite",
            "SodaCan_Spite",
            "SodaCan_Spite",
            "SodaCan_Spite",
            "SodaCan_Spite"
          ],
          "complexChildrenTypes": []
        }
      ]
    },
    {
      "slotName": "Legs",
      "discreteItemSets": [
        {
          "itemType": "FirefightersPants_Black",
          "spawnWeight": 1,
          "attributes": {
            "healthMin": 1,
            "healthMax": 1,
            "quantityMin": 1,
            "quantityMax": 1
          },
          "quickBarSlot": -1,
          "simpleChildrenUseDefaultAttributes": false,
          "simpleChildrenTypes": [
            "Candycane_Red",
            "Honey",
            "Plum",
            "Plum",
            "Plum"
          ],
          "complexChildrenTypes": []
        }
      ]
    },
    {
      "slotName": "Feet",
      "discreteItemSets": [
        {
          "itemType": "Wellies_Black",
          "spawnWeight": 1,
          "attributes": {
            "healthMin": 1,
            "healthMax": 1,
            "quantityMin": 1,
            "quantityMax": 1
          },
          "quickBarSlot": -1,
          "simpleChildrenUseDefaultAttributes": false,
          "simpleChildrenTypes": [],
          "complexChildrenTypes": []
        }
      ]
    },
    {
      "slotName": "Eyewear",
      "discreteItemSets": [
        {
          "itemType": "AviatorGlasses",
          "spawnWeight": 1,
          "attributes": {
            "healthMin": 1,
            "healthMax": 1,
            "quantityMin": 1,
            "quantityMax": 1
          },
          "quickBarSlot": -1,
          "simpleChildrenUseDefaultAttributes": false,
          "simpleChildrenTypes": [],
          "complexChildrenTypes": []
        }
      ]
    },
    {
      "slotName": "Mask",
      "discreteItemSets": [
        {
          "itemType": "BalaclavaMask_Black",
          "spawnWeight": 1,
          "attributes": {
            "healthMin": 1,
            "healthMax": 1,
            "quantityMin": 1,
            "quantityMax": 1
          },
          "quickBarSlot": -1,
          "simpleChildrenUseDefaultAttributes": false,
          "simpleChildrenTypes": [],
          "complexChildrenTypes": []
        }
      ]
    },
    {
      "slotName": "Back",
      "discreteItemSets": [
        {
          "itemType": "ArmyPouch_Black",
          "spawnWeight": 1,
          "attributes": {
            "healthMin": 1,
            "healthMax": 1,
            "quantityMin": 1,
            "quantityMax": 1
          },
          "quickBarSlot": -1,
          "simpleChildrenUseDefaultAttributes": false,
          "simpleChildrenTypes": [
            "Chemlight_White",
            "BandageDressing",
            "BandageDressing",
            "BandageDressing",
            "BandageDressing",
            "BandageDressing",
            "BandageDressing",
            "ChernarusMap",
            "Tomato",
            "Tomato",
            "SodaCan_Spite",
            "SodaCan_Spite"
          ],
          "complexChildrenTypes": [
            {
              "itemType": "PersonalRadio",
              "attributes": {
                "healthMin": 1,
                "healthMax": 1,
                "quantityMin": 1,
                "quantityMax": 1
              },
              "quickBarSlot": -1,
              "simpleChildrenUseDefaultAttributes": true,
              "simpleChildrenTypes": [
                "Battery9V"
              ]
            }
          ]
        }
      ]
    },
    {
      "slotName": "Hips",
      "discreteItemSets": [
        {
          "itemType": "HipPack_Black",
          "spawnWeight": 1,
          "attributes": {
            "healthMin": 1,
            "healthMax": 1,
            "quantityMin": 1,
            "quantityMax": 1
          },
          "quickBarSlot": -1,
          "simpleChildrenUseDefaultAttributes": false,
          "simpleChildrenTypes": [
            "Canteen",
            "SodaCan_Pipsi",
            "SodaCan_Pipsi"
          ],
          "complexChildrenTypes": []
        }
      ]
    }
  ],
  "discreteUnsortedItemSets": [
    {
      "name": "Cargo1",
      "spawnWeight": 1,
      "attributes": {
        "healthMin": 1,
        "healthMax": 1,
        "quantityMin": 1,
        "quantityMax": 1
      },
      "simpleChildrenUseDefaultAttributes": false,
      "simpleChildrenTypes": [
        "ChernarusMap",
        "BandageDressing"
      ],
      "complexChildrenTypes": []
    }
  ]
}